rv_utilities/Utils.py
rv_utilities/__init__.py
rv_utilities-0.2.dist-info/METADATA
rv_utilities-0.2.dist-info/WHEEL
rv_utilities-0.2.dist-info/top_level.txt
rv_utilities-0.2.dist-info/RECORD
