Metadata-Version: 2.1
Name: rv-utilities
Version: 0.2
Summary: rv_utilities package
Home-page: UNKNOWN
Author: Robert
Author-email: robert.valassi@accenture.com
License: MIT
Platform: UNKNOWN
Requires-Python: >=3.7
